dimpy/__init__.py
dimpy/arraydim.py
dimpy-0.0.2.dist-info/METADATA
dimpy-0.0.2.dist-info/WHEEL
dimpy-0.0.2.dist-info/license.txt
dimpy-0.0.2.dist-info/top_level.txt
dimpy-0.0.2.dist-info/RECORD
