Metadata-Version: 2.1
Name: dimpy
Version: 0.0.2
Summary: A package for creating N-dimensional list array
Home-page: https://github.com/dwaipayandeb/dimpy
Author: Dwaipayan Deb
Author-email: dwaipayandeb@yahoo.co.in
License: UNKNOWN
Project-URL: Bug Tracker, https://github.com/dwaipayandeb/dimpy
Platform: UNKNOWN
Classifier: Programming Language :: Python :: 3
Classifier: License :: OSI Approved :: MIT License
Classifier: Operating System :: OS Independent
Requires-Python: >=3.6
